oneplan_sdk/__init__.py
oneplan_sdk/client/README.md
oneplan_sdk/client/api.yaml
oneplan_sdk/client/docs/AccessLevel.md
oneplan_sdk/client/docs/AccessType.md
oneplan_sdk/client/docs/AddResourcePost.md
oneplan_sdk/client/docs/AgileApi.md
oneplan_sdk/client/docs/AllocationClass.md
oneplan_sdk/client/docs/AllocationPost.md
oneplan_sdk/client/docs/AllocationTypes.md
oneplan_sdk/client/docs/AppButton.md
oneplan_sdk/client/docs/AppCostType.md
oneplan_sdk/client/docs/AppDefinition.md
oneplan_sdk/client/docs/AppProperty.md
oneplan_sdk/client/docs/AppsApi.md
oneplan_sdk/client/docs/Assembly.md
oneplan_sdk/client/docs/AssignmentRequest.md
oneplan_sdk/client/docs/AssignmentType.md
oneplan_sdk/client/docs/AsyncProcess.md
oneplan_sdk/client/docs/AsyncProcessResult.md
oneplan_sdk/client/docs/AsyncProcessState.md
oneplan_sdk/client/docs/AsyncProcessStatus.md
oneplan_sdk/client/docs/AuditApi.md
oneplan_sdk/client/docs/AuditFinancialPlans.md
oneplan_sdk/client/docs/AuditFinancialPlansQuery.md
oneplan_sdk/client/docs/AuditPlans.md
oneplan_sdk/client/docs/AuditPlansQuery.md
oneplan_sdk/client/docs/AuditResource.md
oneplan_sdk/client/docs/AuditResourcePlans.md
oneplan_sdk/client/docs/AuditResourcePlansQuery.md
oneplan_sdk/client/docs/AuditResourceQuery.md
oneplan_sdk/client/docs/AuditSharedWith.md
oneplan_sdk/client/docs/AuditSharedWithQuery.md
oneplan_sdk/client/docs/AuditTasks.md
oneplan_sdk/client/docs/AuditTasksQuery.md
oneplan_sdk/client/docs/BoardResponse.md
oneplan_sdk/client/docs/Boolean.md
oneplan_sdk/client/docs/BubbleChartSettings.md
oneplan_sdk/client/docs/ButtonLocation.md
oneplan_sdk/client/docs/CalculationDefinition.md
oneplan_sdk/client/docs/Calendar.md
oneplan_sdk/client/docs/CalendarAlgorithmType.md
oneplan_sdk/client/docs/CalendarWeekRule.md
oneplan_sdk/client/docs/CallingConventions.md
oneplan_sdk/client/docs/CandidatesPost.md
oneplan_sdk/client/docs/CharSet.md
oneplan_sdk/client/docs/ChartType.md
oneplan_sdk/client/docs/ColumnAggEnum.md
oneplan_sdk-0.1.0.dist-info/METADATA
oneplan_sdk-0.1.0.dist-info/WHEEL
oneplan_sdk-0.1.0.dist-info/RECORD
