Metadata-Version: 2.1
Name: oneplan-sdk
Version: 0.1.0
Summary: 
Author: Tsvetan Kintisheff
Author-email: kintisheff@gmail.com
Requires-Python: >=3.12,<4.0
Classifier: Programming Language :: Python :: 3
Classifier: Programming Language :: Python :: 3.12
Requires-Dist: beautifulsoup4 (>=4.12.3,<5.0.0)
Requires-Dist: certifi (>=2024.7.4,<2025.0.0)
Requires-Dist: python-dateutil (>=2.9.0.post0,<3.0.0)
Requires-Dist: python-dotenv (>=1.0.1,<2.0.0)
Requires-Dist: requests (>=2.32.3,<3.0.0)
Requires-Dist: six (>=1.16.0,<2.0.0)
Requires-Dist: urllib3 (>=2.2.2,<3.0.0)
